adspawner/__init__.py
adspawner/_version.py
adspawner/adspawner.py
adspawner-0.3.4.dist-info/LICENSE
adspawner-0.3.4.dist-info/METADATA
adspawner-0.3.4.dist-info/WHEEL
adspawner-0.3.4.dist-info/top_level.txt
adspawner-0.3.4.dist-info/RECORD
